<?xml version="1.0"?>
<!DOCTYPE hibernate-mapping PUBLIC "-//Hibernate/Hibernate Mapping DTD 3.0//EN"
"http://www.hibernate.org/dtd/hibernate-mapping-3.0.dtd">
<!-- Generated 20/09/2023 14:26:59 by Hibernate Tools 3.6.0 -->
<hibernate-mapping>
    <class name="codemarket.model.pojo.TbStatus" table="tb_status" catalog="code_market">
        <id name="staId" type="int">
            <column name="sta_id" />
            <generator class="assigned" />
        </id>
        <property name="staDescricao" type="string">
            <column name="sta_descricao" length="50" not-null="true" />
        </property>
        <set name="tbFuncionarios" table="tb_funcionario" inverse="true" lazy="true" fetch="select">
            <key>
                <column name="func_status" not-null="true" />
            </key>
            <one-to-many class="codemarket.model.pojo.TbFuncionario" />
        </set>
        <set name="tbUsuarios" table="tb_usuario" inverse="true" lazy="true" fetch="select">
            <key>
                <column name="usu_status" not-null="true" />
            </key>
            <one-to-many class="codemarket.model.pojo.TbUsuario" />
        </set>
    </class>
</hibernate-mapping>
